{
	"schemaVersion": 1,
	"id": "statuseffects",
	"version": "${version}",
	"name": "Status Effects",
	"description": "Simple status effects HUD!",
	"authors": [
		"Mixces"
	],
	"contact": {
		"homepage": "",
		"sources": ""
	},
	"license": "CC0-1.0",
	"icon": "assets/statuseffects/icon.png",
	"environment": "*",
	"entrypoints": {
		"init": [
      "me.mixces.statuseffects.StatusEffects"
		]
	},
	"mixins": [
    "statuseffects.mixins.json"
	],
	"depends": {
		"fabricloader": ">=0.14.21",
		"minecraft": "1.8.9",
		"osl-entrypoints": ">=0.4.0"
	}
}
